{
  "data": {
    "article": {},
    "attachments": {
      "media_keys": [
        "3_1998027522575912960"
      ],
      "media_source_tweet_id": [
        "1998362000955670579"
      ]
    },
    "author_id": "1641968587102621696",
    "conversation_id": "1998605231823925525",
    "created_at": "2025-12-10T04:06:34.000Z",
    "edit_controls": {
      "editable_until": "2025-12-10T05:06:34.000Z",
      "edits_remaining": 5,
      "is_edit_eligible": false
    },
    "edit_history_tweet_ids": [
      "1998605231823925525"
    ],
    "entities": {
      "mentions": [
        {
          "end": 15,
          "id": "1298584018531868675",
          "start": 3,
          "username": "sorrrowfull"
        }
      ],
      "urls": [
        {
          "display_url": "pic.x.com/jQJoPtYkRg",
          "end": 40,
          "expanded_url": "https://x.com/sorrrowfull/status/1998362000955670579/photo/1",
          "media_key": "3_1998027522575912960",
          "start": 17,
          "url": "https://t.co/jQJoPtYkRg"
        }
      ]
    },
    "geo": {},
    "id": "1998605231823925525",
    "lang": "zxx",
    "note_tweet": {
      "entities": {}
    },
    "possibly_sensitive": false,
    "public_metrics": {
      "bookmark_count": 0,
      "impression_count": 0,
      "like_count": 0,
      "quote_count": 0,
      "reply_count": 0,
      "retweet_count": 2491
    },
    "referenced_tweets": [
      {
        "id": "1998362000955670579",
        "type": "retweeted"
      }
    ],
    "reply_settings": "everyone",
    "text": "RT @sorrrowfull: https://t.co/jQJoPtYkRg"
  },
  "includes": {
    "media": [
      {
        "height": 540,
        "media_key": "3_1998027522575912960",
        "public_metrics": {},
        "type": "photo",
        "url": "https://pbs.twimg.com/media/G7prch6XUAARKfy.jpg",
        "width": 959
      }
    ],
    "tweets": [
      {
        "article": {},
        "attachments": {
          "media_keys": [
            "3_1998027522575912960"
          ],
          "media_source_tweet_id": [
            "1998362000955670579"
          ]
        },
        "author_id": "1641968587102621696",
        "conversation_id": "1998605231823925525",
        "created_at": "2025-12-10T04:06:34.000Z",
        "edit_controls": {
          "editable_until": "2025-12-10T05:06:34.000Z",
          "edits_remaining": 5,
          "is_edit_eligible": false
        },
        "edit_history_tweet_ids": [
          "1998605231823925525"
        ],
        "entities": {
          "mentions": [
            {
              "end": 15,
              "id": "1298584018531868675",
              "start": 3,
              "username": "sorrrowfull"
            }
          ],
          "urls": [
            {
              "display_url": "pic.x.com/jQJoPtYkRg",
              "end": 40,
              "expanded_url": "https://x.com/sorrrowfull/status/1998362000955670579/photo/1",
              "media_key": "3_1998027522575912960",
              "start": 17,
              "url": "https://t.co/jQJoPtYkRg"
            }
          ]
        },
        "geo": {},
        "id": "1998605231823925525",
        "lang": "zxx",
        "note_tweet": {
          "entities": {}
        },
        "possibly_sensitive": false,
        "public_metrics": {
          "bookmark_count": 0,
          "impression_count": 0,
          "like_count": 0,
          "quote_count": 0,
          "reply_count": 0,
          "retweet_count": 2491
        },
        "referenced_tweets": [
          {
            "id": "1998362000955670579",
            "type": "retweeted"
          }
        ],
        "reply_settings": "everyone",
        "text": "RT @sorrrowfull: https://t.co/jQJoPtYkRg"
      },
      {
        "article": {},
        "attachments": {
          "media_keys": [
            "3_1998027522575912960"
          ]
        },
        "author_id": "1298584018531868675",
        "conversation_id": "1998362000955670579",
        "created_at": "2025-12-09T12:00:03.000Z",
        "edit_controls": {
          "editable_until": "2025-12-09T13:00:03.000Z",
          "edits_remaining": 5,
          "is_edit_eligible": true
        },
        "edit_history_tweet_ids": [
          "1998362000955670579"
        ],
        "entities": {
          "urls": [
            {
              "display_url": "pic.x.com/jQJoPtYkRg",
              "end": 23,
              "expanded_url": "https://x.com/sorrrowfull/status/1998362000955670579/photo/1",
              "media_key": "3_1998027522575912960",
              "start": 0,
              "url": "https://t.co/jQJoPtYkRg"
            }
          ]
        },
        "geo": {},
        "id": "1998362000955670579",
        "lang": "zxx",
        "note_tweet": {
          "entities": {}
        },
        "possibly_sensitive": false,
        "public_metrics": {
          "bookmark_count": 723,
          "impression_count": 324443,
          "like_count": 19563,
          "quote_count": 34,
          "reply_count": 15,
          "retweet_count": 2491
        },
        "reply_settings": "everyone",
        "text": "https://t.co/jQJoPtYkRg"
      }
    ],
    "users": [
      {
        "created_at": "2023-04-01T01:00:11.000Z",
        "description": "♡⃝OD♡⃝自伤♡⃝绘画♡⃝-------------------查成分回fo -------------------------------顺女 什么都发 接受一切 立场是关我屁事",
        "id": "1641968587102621696",
        "location": "淚",
        "name": "RuN4wAY",
        "pinned_tweet_id": "1998061954095853671",
        "profile_image_url": "https://pbs.twimg.com/profile_images/1997581025162207232/QHUo0McK_normal.jpg",
        "protected": false,
        "public_metrics": {
          "followers_count": 57,
          "following_count": 388,
          "like_count": 872,
          "listed_count": 0,
          "media_count": 30,
          "tweet_count": 393
        },
        "username": "0voki33Me",
        "verified": false
      },
      {
        "created_at": "2020-08-26T11:32:35.000Z",
        "description": "",
        "entities": {
          "url": {
            "urls": [
              {
                "display_url": "instagram.com/sorrowfulhiv",
                "end": 23,
                "expanded_url": "http://instagram.com/sorrowfulhiv",
                "start": 0,
                "url": "https://t.co/XRnrJ5RG1F"
              }
            ]
          }
        },
        "id": "1298584018531868675",
        "name": "hîv.",
        "pinned_tweet_id": "1998340699163435201",
        "profile_image_url": "https://pbs.twimg.com/profile_images/1545392133422698498/bssWLQiJ_normal.jpg",
        "protected": false,
        "public_metrics": {
          "followers_count": 172053,
          "following_count": 52,
          "like_count": 5565,
          "listed_count": 632,
          "media_count": 6790,
          "tweet_count": 7897
        },
        "url": "https://t.co/XRnrJ5RG1F",
        "username": "sorrrowfull",
        "verified": true
      }
    ]
  }
}