{
  "data": {
    "article": {},
    "attachments": {},
    "author_id": "1641968587102621696",
    "context_annotations": [
      {
        "domain": {
          "description": "Named people in the world like Nelson Mandela",
          "id": "10",
          "name": "Person"
        },
        "entity": {
          "id": "1183731875715543040",
          "name": "Sulli"
        }
      },
      {
        "domain": {
          "description": "A musician in the world, like Adele or Bob Dylan",
          "id": "54",
          "name": "Musician"
        },
        "entity": {
          "id": "1183731875715543040",
          "name": "Sulli"
        }
      },
      {
        "domain": {
          "description": "A category for a musical style, like Pop, Rock, or Rap",
          "id": "55",
          "name": "Music Genre"
        },
        "entity": {
          "description": "K-Pop",
          "id": "888105153038958593",
          "name": "K-pop"
        }
      }
    ],
    "conversation_id": "2045206296723603628",
    "created_at": "2026-04-17T18:22:33.000Z",
    "edit_controls": {
      "editable_until": "2026-04-17T19:22:33.000Z",
      "edits_remaining": 5,
      "is_edit_eligible": true
    },
    "edit_history_tweet_ids": [
      "2045206296723603628"
    ],
    "entities": {
      "urls": [
        {
          "display_url": "x.com/sullves/status…",
          "end": 52,
          "expanded_url": "https://twitter.com/sullves/status/2043699981404479979",
          "start": 29,
          "url": "https://t.co/Ha9wWgMWc0"
        }
      ]
    },
    "geo": {},
    "id": "2045206296723603628",
    "lang": "zh",
    "note_tweet": {
      "entities": {}
    },
    "possibly_sensitive": false,
    "public_metrics": {
      "bookmark_count": 0,
      "impression_count": 0,
      "like_count": 0,
      "quote_count": 0,
      "reply_count": 0,
      "retweet_count": 0
    },
    "referenced_tweets": [
      {
        "id": "2043699981404479979",
        "type": "quoted"
      }
    ],
    "reply_settings": "everyone",
    "text": "我就觉得他俩好像，雪莉重活一世哦对不起有点像诅咒，我错了 https://t.co/Ha9wWgMWc0"
  },
  "includes": {
    "media": [
      {
        "height": 1080,
        "media_key": "3_2043699978648891392",
        "public_metrics": {},
        "type": "photo",
        "url": "https://pbs.twimg.com/media/HFyuTXbXMAAzNng.jpg",
        "width": 1080
      },
      {
        "height": 439,
        "media_key": "3_2043699979592814592",
        "public_metrics": {},
        "type": "photo",
        "url": "https://pbs.twimg.com/media/HFyuTa8aUAASC68.jpg",
        "width": 439
      }
    ],
    "tweets": [
      {
        "article": {},
        "attachments": {},
        "author_id": "1641968587102621696",
        "context_annotations": [
          {
            "domain": {
              "description": "Named people in the world like Nelson Mandela",
              "id": "10",
              "name": "Person"
            },
            "entity": {
              "id": "1183731875715543040",
              "name": "Sulli"
            }
          },
          {
            "domain": {
              "description": "A musician in the world, like Adele or Bob Dylan",
              "id": "54",
              "name": "Musician"
            },
            "entity": {
              "id": "1183731875715543040",
              "name": "Sulli"
            }
          },
          {
            "domain": {
              "description": "A category for a musical style, like Pop, Rock, or Rap",
              "id": "55",
              "name": "Music Genre"
            },
            "entity": {
              "description": "K-Pop",
              "id": "888105153038958593",
              "name": "K-pop"
            }
          }
        ],
        "conversation_id": "2045206296723603628",
        "created_at": "2026-04-17T18:22:33.000Z",
        "edit_controls": {
          "editable_until": "2026-04-17T19:22:33.000Z",
          "edits_remaining": 5,
          "is_edit_eligible": true
        },
        "edit_history_tweet_ids": [
          "2045206296723603628"
        ],
        "entities": {
          "urls": [
            {
              "display_url": "x.com/sullves/status…",
              "end": 52,
              "expanded_url": "https://twitter.com/sullves/status/2043699981404479979",
              "start": 29,
              "url": "https://t.co/Ha9wWgMWc0"
            }
          ]
        },
        "geo": {},
        "id": "2045206296723603628",
        "lang": "zh",
        "note_tweet": {
          "entities": {}
        },
        "possibly_sensitive": false,
        "public_metrics": {
          "bookmark_count": 0,
          "impression_count": 0,
          "like_count": 0,
          "quote_count": 0,
          "reply_count": 0,
          "retweet_count": 0
        },
        "referenced_tweets": [
          {
            "id": "2043699981404479979",
            "type": "quoted"
          }
        ],
        "reply_settings": "everyone",
        "text": "我就觉得他俩好像，雪莉重活一世哦对不起有点像诅咒，我错了 https://t.co/Ha9wWgMWc0"
      },
      {
        "article": {},
        "attachments": {
          "media_keys": [
            "3_2043699978648891392",
            "3_2043699979592814592"
          ]
        },
        "author_id": "1452086653468676096",
        "context_annotations": [
          {
            "domain": {
              "description": "Named people in the world like Nelson Mandela",
              "id": "10",
              "name": "Person"
            },
            "entity": {
              "id": "1183731875715543040",
              "name": "Sulli"
            }
          },
          {
            "domain": {
              "description": "A musician in the world, like Adele or Bob Dylan",
              "id": "54",
              "name": "Musician"
            },
            "entity": {
              "id": "1183731875715543040",
              "name": "Sulli"
            }
          },
          {
            "domain": {
              "description": "A category for a musical style, like Pop, Rock, or Rap",
              "id": "55",
              "name": "Music Genre"
            },
            "entity": {
              "description": "K-Pop",
              "id": "888105153038958593",
              "name": "K-pop"
            }
          }
        ],
        "conversation_id": "2043699981404479979",
        "created_at": "2026-04-13T14:37:00.000Z",
        "edit_controls": {
          "editable_until": "2026-04-13T15:37:00.000Z",
          "edits_remaining": 5,
          "is_edit_eligible": true
        },
        "edit_history_tweet_ids": [
          "2043699981404479979"
        ],
        "entities": {
          "hashtags": [
            {
              "end": 26,
              "start": 21,
              "tag": "YVES"
            },
            {
              "end": 30,
              "start": 27,
              "tag": "이브"
            },
            {
              "end": 37,
              "start": 31,
              "tag": "SULLI"
            },
            {
              "end": 42,
              "start": 38,
              "tag": "최진리"
            }
          ],
          "urls": [
            {
              "display_url": "pic.x.com/eDoZ9qCxMi",
              "end": 66,
              "expanded_url": "https://x.com/sullves/status/2043699981404479979/photo/1",
              "media_key": "3_2043699978648891392",
              "start": 43,
              "url": "https://t.co/eDoZ9qCxMi"
            },
            {
              "display_url": "pic.x.com/eDoZ9qCxMi",
              "end": 66,
              "expanded_url": "https://x.com/sullves/status/2043699981404479979/photo/1",
              "media_key": "3_2043699979592814592",
              "start": 43,
              "url": "https://t.co/eDoZ9qCxMi"
            }
          ]
        },
        "geo": {},
        "id": "2043699981404479979",
        "lang": "en",
        "note_tweet": {
          "entities": {}
        },
        "possibly_sensitive": false,
        "public_metrics": {
          "bookmark_count": 9,
          "impression_count": 2270,
          "like_count": 186,
          "quote_count": 2,
          "reply_count": 3,
          "retweet_count": 16
        },
        "reply_settings": "everyone",
        "text": "who remembers me....\n#YVES #이브 #SULLI #최진리 https://t.co/eDoZ9qCxMi"
      }
    ],
    "users": [
      {
        "created_at": "2023-04-01T01:00:11.000Z",
        "description": "该账号什么都发不为任何言行负责｜只回fo感兴趣的｜提问箱⬇️",
        "entities": {
          "url": {
            "urls": [
              {
                "display_url": "ngl.link/0voki33me",
                "end": 23,
                "expanded_url": "https://ngl.link/0voki33me",
                "start": 0,
                "url": "https://t.co/Dhfap4dheT"
              }
            ]
          }
        },
        "id": "1641968587102621696",
        "location": "👽👽",
        "name": "4w4y",
        "pinned_tweet_id": "2024513212876767280",
        "profile_image_url": "https://pbs.twimg.com/profile_images/2025267837263380484/sO1VN491_normal.jpg",
        "protected": false,
        "public_metrics": {
          "followers_count": 657,
          "following_count": 1144,
          "like_count": 6217,
          "listed_count": 0,
          "media_count": 290,
          "tweet_count": 5755
        },
        "url": "https://t.co/Dhfap4dheT",
        "username": "0voki33Me",
        "verified": false
      },
      {
        "created_at": "2021-10-24T01:36:57.000Z",
        "description": "thinking about yvesri  |  dm submissions !",
        "id": "1452086653468676096",
        "location": "they/them",
        "name": "sulli + yves agenda",
        "pinned_tweet_id": "1802740071428169738",
        "profile_image_url": "https://pbs.twimg.com/profile_images/1896586470913130496/_KNjaB6I_normal.jpg",
        "protected": false,
        "public_metrics": {
          "followers_count": 848,
          "following_count": 70,
          "like_count": 487,
          "listed_count": 2,
          "media_count": 278,
          "tweet_count": 295
        },
        "username": "sullves",
        "verified": false
      }
    ]
  }
}